rmc_mcp/__init__.py
rmc_mcp/prompts.py
rmc_mcp/server.py
rmc_mcp-0.1.0.dist-info/METADATA
rmc_mcp-0.1.0.dist-info/WHEEL
rmc_mcp-0.1.0.dist-info/entry_points.txt
rmc_mcp-0.1.0.dist-info/licenses/LICENSE
rmc_mcp-0.1.0.dist-info/RECORD
