Metadata-Version: 2.4
Name: rmc-mcp
Version: 0.1.0
Summary: Recursive Meta-Cognition MCP Server - wraps prompts with meta-cognition instructions for AI code assistants
Project-URL: Homepage, https://github.com/gumruyanzh/rmc-mcp
Project-URL: Repository, https://github.com/gumruyanzh/rmc-mcp
Project-URL: Issues, https://github.com/gumruyanzh/rmc-mcp/issues
Author-email: gumruyanzh <gumruyanzh@users.noreply.github.com>
License-Expression: MIT
License-File: LICENSE
Keywords: ai,claude,deepseek,llm,mcp,meta-cognition,prompt-engineering
Classifier: Development Status :: 4 - Beta
Classifier: Intended Audience :: Developers
Classifier: License :: OSI Approved :: MIT License
Classifier: Programming Language :: Python :: 3
Classifier: Programming Language :: Python :: 3.10
Classifier: Programming Language :: Python :: 3.11
Classifier: Programming Language :: Python :: 3.12
Classifier: Topic :: Scientific/Engineering :: Artificial Intelligence
Classifier: Topic :: Software Development :: Libraries :: Python Modules
Requires-Python: >=3.10
Requires-Dist: mcp[cli]>=1.25.0
Requires-Dist: openai>=1.50.0
